{"web":{"client_id":"387945826280-v2n2jmu9bijb9k6jv7ua67c5ionorocf.apps.googleusercontent.com","auth_uri":"https://accounts.google.com/o/oauth2/auth","token_uri":"https://accounts.google.com/o/oauth2/token","auth_provider_x509_cert_url":"https://www.googleapis.com/oauth2/v1/certs","client_email":"387945826280-v2n2jmu9bijb9k6jv7ua67c5ionorocf@developer.gserviceaccount.com","client_x509_cert_url":"https://www.googleapis.com/robot/v1/metadata/x509/387945826280-v2n2jmu9bijb9k6jv7ua67c5ionorocf%40developer.gserviceaccount.com","client_secret":"1WKl1A2phrKKffkxAAveEXi2","redirect_uris":["https://www.example.com/oauth2callback"],"javascript_origins":["https://www.example.com","http://localhost:5000"]}}